aristotle/__init__.py
aristotle/__main__.py
aristotle/aristotle.py
aristotle-2.1.0.dist-info/LICENSE
aristotle-2.1.0.dist-info/METADATA
aristotle-2.1.0.dist-info/WHEEL
aristotle-2.1.0.dist-info/top_level.txt
aristotle-2.1.0.dist-info/RECORD
