Metadata-Version: 2.1
Name: aristotle
Version: 2.1.0
Summary: Script and library for the viewing, filtering, and modifying of Suricata and Snort rulesets based on interpreted key-value pairs present in the metadata keyword within each rule.
Home-page: https://github.com/secureworks/aristotle
Author: David Wharton
Project-URL: Documentation, https://aristotle-py.readthedocs.io/
Project-URL: Source, https://github.com/secureworks/aristotle
Keywords: suricata,snort,metadata,ruleset,BETTER,IDS,IPS,NIDS,signatures
Classifier: Development Status :: 5 - Production/Stable
Classifier: Programming Language :: Python :: 2.7
Classifier: Programming Language :: Python :: 3
Classifier: License :: OSI Approved :: Apache Software License
Classifier: Operating System :: OS Independent
Classifier: Intended Audience :: Information Technology
Classifier: Intended Audience :: Developers
Classifier: Topic :: System :: Networking :: Monitoring
Classifier: Topic :: System :: Networking :: Firewalls
Requires-Python: >=2.7
License-File: LICENSE
Requires-Dist: boolean.py <=3.8,>=3.6
Requires-Dist: python-dateutil
Requires-Dist: pyyaml
